odoo/addons/base_confirmation_requirement_rules/README.rst
odoo/addons/base_confirmation_requirement_rules/__init__.py
odoo/addons/base_confirmation_requirement_rules/__manifest__.py
odoo/addons/base_confirmation_requirement_rules/data/confirmation_requirement_data.xml
odoo/addons/base_confirmation_requirement_rules/i18n/es.po
odoo/addons/base_confirmation_requirement_rules/models/__init__.py
odoo/addons/base_confirmation_requirement_rules/models/confirmation_requirement_mixin.py
odoo/addons/base_confirmation_requirement_rules/models/confirmation_requirement_rule_mixin.py
odoo/addons/base_confirmation_requirement_rules/models/requirement_rule_type_mixin.py
odoo/addons/base_confirmation_requirement_rules/static/description/icon.png
odoo_addon_base_confirmation_requirement_rules-15.0.1.0.0.1.dist-info/METADATA
odoo_addon_base_confirmation_requirement_rules-15.0.1.0.0.1.dist-info/WHEEL
odoo_addon_base_confirmation_requirement_rules-15.0.1.0.0.1.dist-info/top_level.txt
odoo_addon_base_confirmation_requirement_rules-15.0.1.0.0.1.dist-info/RECORD
