Metadata-Version: 2.1
Name: odoo-addon-base_confirmation_requirement_rules
Version: 15.0.1.0.0.1
Requires-Python: >=3.8
Requires-Dist: odoo>=15.0a,<15.1dev
Summary: Base module to set confirmation requirement rules.
Home-page: https://github.com/sygel-technology/sy-server-tools
License: AGPL-3
Author: Sygel, Odoo Community Association (OCA)
Author-email: support@odoo-community.org
Classifier: Programming Language :: Python
Classifier: Framework :: Odoo
Classifier: Framework :: Odoo :: 15.0
Classifier: License :: OSI Approved :: GNU Affero General Public License v3
